{"40327936": {"tags": ["python", "pandas", "pyspark"], "question_id": 40327936, "title": "pandas TimeGrouper in PySpark", "view_count": 16, "link": "http://stackoverflow.com/questions/40327936/pandas-timegrouper-in-pyspark", "owner": {"profile_image": "https://www.gravatar.com/avatar/b9e39de46b5a7e52e314cbb5008f1fbf?s=128&d=identicon&r=PG&f=1", "display_name": "Menkes", "user_type": "registered", "accept_rate": 56, "user_id": 5563746, "reputation": 109, "link": "http://stackoverflow.com/users/5563746/menkes"}, "score": 0, "is_answered": false, "creation_date": 1477822035, "answer_count": 0, "last_activity_date": 1477822035}, "40171777": {"tags": ["python", "pandas"], "title": "Add columns and values to pandas DataFrame", "owner": {"profile_image": "https://www.gravatar.com/avatar/ae2d1aef741a89e2208608c32cae6b59?s=128&d=identicon&r=PG&f=1", "display_name": "Probs", "user_type": "registered", "accept_rate": 40, "user_id": 6555655, "reputation": 18, "link": "http://stackoverflow.com/users/6555655/probs"}, "score": 0, "creation_date": 1477038367, "last_edit_date": 1477050944, "last_activity_date": 1477050944, "question_id": 40171777, "view_count": 41, "is_answered": false, "answer_count": 0, "link": "http://stackoverflow.com/questions/40171777/add-columns-and-values-to-pandas-dataframe"}, "40090710": {"tags": ["python", "json", "pandas"], "title": "Select specific fields from nested json data", "owner": {"profile_image": "https://www.gravatar.com/avatar/bbf5112d190ea1089d347ac74198b968?s=128&d=identicon&r=PG&f=1", "display_name": "Anne", "user_type": "registered", "user_id": 7013161, "reputation": 11, "link": "http://stackoverflow.com/users/7013161/anne"}, "score": 0, "creation_date": 1476719428, "last_edit_date": 1476772939, "last_activity_date": 1476772939, "question_id": 40090710, "view_count": 29, "is_answered": false, "answer_count": 0, "link": "http://stackoverflow.com/questions/40090710/select-specific-fields-from-nested-json-data"}, "40041222": {"tags": ["python", "pandas", "codec"], "title": "CSV file Parsing issue because of unintended characters (CParserError: Error tokenizing data) in Pandas", "owner": {"profile_image": "https://www.gravatar.com/avatar/7cdee843e31c0b50cf0daec2d228be50?s=128&d=identicon&r=PG", "display_name": "user1829708", "user_type": "registered", "user_id": 1829708, "reputation": 14, "link": "http://stackoverflow.com/users/1829708/user1829708"}, "score": 0, "creation_date": 1476441773, "last_edit_date": 1476641473, "last_activity_date": 1476641473, "question_id": 40041222, "view_count": 27, "is_answered": false, "answer_count": 0, "link": "http://stackoverflow.com/questions/40041222/csv-file-parsing-issue-because-of-unintended-characters-cparsererror-error-tok"}, "40320013": {"tags": ["python", "pandas", "scikit-learn"], "title": "Can&#39;t import sicikit-learn and pandas", "owner": {"profile_image": "https://www.gravatar.com/avatar/1ac20d3440e8c6986c8dccc00ee12220?s=128&d=identicon&r=PG&f=1", "display_name": "PythIsReal", "user_type": "registered", "user_id": 6539484, "reputation": 7, "link": "http://stackoverflow.com/users/6539484/pythisreal"}, "score": -3, "creation_date": 1477750834, "last_edit_date": 1477752321, "last_activity_date": 1477752321, "question_id": 40320013, "view_count": 34, "is_answered": false, "answer_count": 0, "link": "http://stackoverflow.com/questions/40320013/cant-import-sicikit-learn-and-pandas"}, "40353555": {"tags": ["python", "pandas"], "question_id": 40353555, "title": "Backreference in Pandas str.replace", "view_count": 16, "link": "http://stackoverflow.com/questions/40353555/backreference-in-pandas-str-replace", "owner": {"profile_image": "https://www.gravatar.com/avatar/28ac505c39a1d4c37ffe6fc8f8c24e36?s=128&d=identicon&r=PG&f=1", "display_name": "Maven", "user_type": "registered", "accept_rate": 33, "user_id": 2369867, "reputation": 345, "link": "http://stackoverflow.com/users/2369867/maven"}, "score": 0, "is_answered": false, "creation_date": 1477969309, "answer_count": 0, "last_activity_date": 1477971892}, "40050201": {"tags": ["python", "pandas"], "title": "Index pandas df, find match based on column D, E, F, write values from column C to column B", "owner": {"profile_image": "https://www.gravatar.com/avatar/8ccdded9f73b415b9ebc03f79f422f3e?s=128&d=identicon&r=PG&f=1", "display_name": "User9123", "user_type": "registered", "user_id": 7020856, "reputation": 6, "link": "http://stackoverflow.com/users/7020856/user9123"}, "score": -1, "creation_date": 1476471202, "last_edit_date": 1476982644, "last_activity_date": 1476982644, "question_id": 40050201, "view_count": 26, "is_answered": false, "answer_count": 0, "link": "http://stackoverflow.com/questions/40050201/index-pandas-df-find-match-based-on-column-d-e-f-write-values-from-column-c"}, "40157978": {"tags": ["python", "pandas", "scipy", "scikit-learn", "tf-idf"], "question_id": 40157978, "title": "Scikit Learn Find most representative words by TFIDF, in subset of entire corpus", "view_count": 17, "link": "http://stackoverflow.com/questions/40157978/scikit-learn-find-most-representative-words-by-tfidf-in-subset-of-entire-corpus", "owner": {"profile_image": "https://www.gravatar.com/avatar/0c99eed0c23ce6311a7e384093b2f9a8?s=128&d=identicon&r=PG&f=1", "display_name": "James Allen-Robertson", "user_type": "registered", "accept_rate": 100, "user_id": 4796629, "reputation": 46, "link": "http://stackoverflow.com/users/4796629/james-allen-robertson"}, "score": 0, "is_answered": false, "creation_date": 1476975512, "answer_count": 0, "last_activity_date": 1476975512}, "40327963": {"tags": ["python", "pandas", "numpy"], "title": "How to fill missing Timestamp values in padas data frame", "owner": {"profile_image": "https://www.gravatar.com/avatar/82616b6ecfde8a8d770ce90e9a5ac053?s=128&d=identicon&r=PG&f=1", "display_name": "Sayed Zainul Abideen", "user_type": "registered", "user_id": 2550866, "reputation": 340, "link": "http://stackoverflow.com/users/2550866/sayed-zainul-abideen"}, "score": -1, "creation_date": 1477822257, "last_edit_date": 1477827321, "last_activity_date": 1477827321, "question_id": 40327963, "view_count": 35, "is_answered": false, "answer_count": 0, "link": "http://stackoverflow.com/questions/40327963/how-to-fill-missing-timestamp-values-in-padas-data-frame"}, "40206877": {"tags": ["python", "pandas"], "question_id": 40206877, "title": "error concatenating multiindex pandas dataframes (categorical)", "view_count": 20, "link": "http://stackoverflow.com/questions/40206877/error-concatenating-multiindex-pandas-dataframes-categorical", "owner": {"profile_image": "https://lh6.googleusercontent.com/-TOp-QTMQJ7Y/AAAAAAAAAAI/AAAAAAAAFiI/MwmBvJaIs-U/photo.jpg?sz=128", "display_name": "Victor Chubukov", "user_type": "registered", "user_id": 6054326, "reputation": 389, "link": "http://stackoverflow.com/users/6054326/victor-chubukov"}, "score": 1, "is_answered": false, "creation_date": 1477250337, "answer_count": 0, "last_activity_date": 1477250337}, "40332319": {"tags": ["python", "sql-server", "pandas"], "question_id": 40332319, "title": "Writing Pandas&#39; dataframe into SQL Servet table", "view_count": 11, "link": "http://stackoverflow.com/questions/40332319/writing-pandas-dataframe-into-sql-servet-table", "owner": {"profile_image": "https://www.gravatar.com/avatar/7ae3069bce34ea67aa6ed85035fac697?s=128&d=identicon&r=PG", "display_name": "user1700890", "user_type": "registered", "accept_rate": 74, "user_id": 1700890, "reputation": 671, "link": "http://stackoverflow.com/users/1700890/user1700890"}, "score": 0, "is_answered": false, "creation_date": 1477852768, "answer_count": 0, "last_activity_date": 1477852768}, "40346400": {"tags": ["python", "pandas"], "title": "List of diverse lists to sorted pandas data frame", "owner": {"profile_image": "https://i.stack.imgur.com/a6Yzw.jpg?s=128&g=1", "display_name": "SpyTh", "user_type": "registered", "accept_rate": 0, "user_id": 6459589, "reputation": 76, "link": "http://stackoverflow.com/users/6459589/spyth"}, "score": -1, "creation_date": 1477931284, "last_edit_date": 1477934653, "last_activity_date": 1477934653, "question_id": 40346400, "view_count": 34, "is_answered": false, "answer_count": 0, "link": "http://stackoverflow.com/questions/40346400/list-of-diverse-lists-to-sorted-pandas-data-frame"}, "40089889": {"tags": ["python", "python-3.x", "pandas", "grouping"], "question_id": 40089889, "title": "How to replace values in &#171;groupby&#187; (python) object?", "view_count": 53, "link": "http://stackoverflow.com/questions/40089889/how-to-replace-values-in-groupby-python-object", "owner": {"profile_image": "https://i.stack.imgur.com/1jTum.jpg?s=128&g=1", "display_name": "Valentina Biryukova", "user_type": "registered", "user_id": 7030731, "reputation": 1, "link": "http://stackoverflow.com/users/7030731/valentina-biryukova"}, "score": 0, "is_answered": false, "creation_date": 1476716935, "answer_count": 0, "last_activity_date": 1476716935}, "40270627": {"tags": ["python", "pandas"], "question_id": 40270627, "title": "Pandas returning empty groups in groupby", "view_count": 39, "link": "http://stackoverflow.com/questions/40270627/pandas-returning-empty-groups-in-groupby", "owner": {"profile_image": "https://www.gravatar.com/avatar/21b31222e990b631fee5484a7115a991?s=128&d=identicon&r=PG", "display_name": "Oliver", "user_type": "registered", "accept_rate": 59, "user_id": 1431244, "reputation": 2026, "link": "http://stackoverflow.com/users/1431244/oliver"}, "score": 2, "is_answered": false, "creation_date": 1477509996, "answer_count": 0, "last_activity_date": 1477509996}, "40224038": {"tags": ["python", "python-2.7", "pandas", "glob"], "title": "How do I create a class that merges and returns a dataframe, but inherits from another class?", "owner": {"profile_image": "https://www.gravatar.com/avatar/020ce17cc9cadeada53eed3f23758b49?s=128&d=identicon&r=PG&f=1", "display_name": "staten12", "user_type": "registered", "accept_rate": 44, "user_id": 6295849, "reputation": 54, "link": "http://stackoverflow.com/users/6295849/staten12"}, "score": 0, "creation_date": 1477329758, "last_edit_date": 1477331216, "last_activity_date": 1477331216, "question_id": 40224038, "view_count": 31, "is_answered": false, "answer_count": 0, "link": "http://stackoverflow.com/questions/40224038/how-do-i-create-a-class-that-merges-and-returns-a-dataframe-but-inherits-from-a"}, "40117799": {"tags": ["python", "python-3.x", "pandas"], "question_id": 40117799, "title": "Python: Pandas, Text File to DataFrame", "view_count": 34, "link": "http://stackoverflow.com/questions/40117799/python-pandas-text-file-to-dataframe", "owner": {"profile_image": "https://graph.facebook.com/433292986881201/picture?type=large", "display_name": "Destroxia", "user_type": "registered", "accept_rate": 78, "user_id": 5584020, "reputation": 63, "link": "http://stackoverflow.com/users/5584020/destroxia"}, "score": 0, "is_answered": false, "creation_date": 1476823669, "answer_count": 0, "last_activity_date": 1476823669}, "40347689": {"tags": ["python", "pandas", "dataframe"], "question_id": 40347689, "title": "dataframe.describe() suppress scientific notation", "view_count": 10, "link": "http://stackoverflow.com/questions/40347689/dataframe-describe-suppress-scientific-notation", "owner": {"profile_image": "https://www.gravatar.com/avatar/f485c69dfe40c241f3f53d63ea27aa1f?s=128&d=identicon&r=PG&f=1", "display_name": "mfabi", "user_type": "registered", "user_id": 6135337, "reputation": 1, "link": "http://stackoverflow.com/users/6135337/mfabi"}, "score": 0, "is_answered": false, "creation_date": 1477936265, "answer_count": 0, "last_activity_date": 1477936265}, "40349226": {"tags": ["python", "pandas", "plot", "dataframe", "boxplot"], "title": "How to plot on box plot 2 data from different data frama - Python", "owner": {"profile_image": "https://lh6.googleusercontent.com/-MTsq6jGgD3g/AAAAAAAAAAI/AAAAAAAAAYo/GuiQztfX8ew/photo.jpg?sz=128", "display_name": "Rafael Rodrigues Santos", "user_type": "registered", "user_id": 6781190, "reputation": 20, "link": "http://stackoverflow.com/users/6781190/rafael-rodrigues-santos"}, "score": 0, "creation_date": 1477942143, "last_edit_date": 1477942549, "last_activity_date": 1477942549, "question_id": 40349226, "view_count": 12, "is_answered": false, "answer_count": 0, "link": "http://stackoverflow.com/questions/40349226/how-to-plot-on-box-plot-2-data-from-different-data-frama-python"}, "40157485": {"tags": ["python", "datetime", "pandas", "diff"], "title": "Pandas - Function to have to tell if event happened on consecutive days", "owner": {"profile_image": "https://www.gravatar.com/avatar/552889e3ff579575424f280c57cdc747?s=128&d=identicon&r=PG", "display_name": "Kelly Roper", "user_type": "registered", "accept_rate": 72, "user_id": 941759, "reputation": 160, "link": "http://stackoverflow.com/users/941759/kelly-roper"}, "score": 0, "creation_date": 1476974217, "last_edit_date": 1476975643, "last_activity_date": 1476975643, "question_id": 40157485, "view_count": 31, "is_answered": false, "answer_count": 0, "link": "http://stackoverflow.com/questions/40157485/pandas-function-to-have-to-tell-if-event-happened-on-consecutive-days"}, "40272942": {"tags": ["python", "pandas"], "question_id": 40272942, "title": "Why do some methods not have an inplace option? [Pandas]", "view_count": 21, "link": "http://stackoverflow.com/questions/40272942/why-do-some-methods-not-have-an-inplace-option-pandas", "owner": {"profile_image": "https://www.gravatar.com/avatar/a64cb44750d7e7468d8e74d947d04f59?s=128&d=identicon&r=PG&f=1", "display_name": "FuchsMussTun", "user_type": "registered", "user_id": 7066758, "reputation": 1, "link": "http://stackoverflow.com/users/7066758/fuchsmusstun"}, "score": -1, "is_answered": false, "creation_date": 1477519929, "answer_count": 0, "last_activity_date": 1477519929}, "40332336": {"tags": ["python", "loops", "pandas", "scikit-learn"], "title": "Print Knn prediction alongside id", "owner": {"profile_image": "https://lh4.googleusercontent.com/-hjpSYH_37i4/AAAAAAAAAAI/AAAAAAAAAFc/SP4HPI--B0k/photo.jpg?sz=128", "display_name": "Liam Hanninen", "user_type": "registered", "accept_rate": 0, "user_id": 5479704, "reputation": 76, "link": "http://stackoverflow.com/users/5479704/liam-hanninen"}, "score": 0, "creation_date": 1477852876, "last_edit_date": 1477854740, "last_activity_date": 1477854740, "question_id": 40332336, "view_count": 18, "is_answered": false, "answer_count": 0, "link": "http://stackoverflow.com/questions/40332336/print-knn-prediction-alongside-id"}, "40285745": {"tags": ["python", "html", "css", "pandas", "dataframe"], "title": "Setting HTML attributes with Pandas styler for displaying dataframes", "owner": {"profile_image": "https://www.gravatar.com/avatar/fc67f3de09d8a0d4f7af59c5f38bc2ed?s=128&d=identicon&r=PG&f=1", "display_name": "klib", "user_type": "registered", "accept_rate": 100, "user_id": 3814425, "reputation": 350, "link": "http://stackoverflow.com/users/3814425/klib"}, "score": 0, "creation_date": 1477574526, "last_edit_date": 1477576339, "last_activity_date": 1477576339, "question_id": 40285745, "view_count": 31, "is_answered": false, "answer_count": 0, "link": "http://stackoverflow.com/questions/40285745/setting-html-attributes-with-pandas-styler-for-displaying-dataframes"}, "40262195": {"tags": ["python", "pandas", "dataframe", "group-by"], "title": "Rolling Mean with Groupby object in Pandas returns null", "owner": {"profile_image": "https://www.gravatar.com/avatar/af0169e87522d77af3ef81d3442c33c1?s=128&d=identicon&r=PG&f=1", "display_name": "Aris", "user_type": "registered", "user_id": 7074913, "reputation": 8, "link": "http://stackoverflow.com/users/7074913/aris"}, "score": 0, "creation_date": 1477484545, "last_edit_date": 1477491208, "last_activity_date": 1477491208, "question_id": 40262195, "view_count": 31, "is_answered": false, "answer_count": 0, "link": "http://stackoverflow.com/questions/40262195/rolling-mean-with-groupby-object-in-pandas-returns-null"}, "40191650": {"tags": ["python", "pandas", "elasticsearch", "tweepy"], "title": "Getting error KeyError: &#39;retweeted_status&#39; while reading nested json document", "owner": {"profile_image": "https://lh5.googleusercontent.com/-rm8tUGC_tkc/AAAAAAAAAAI/AAAAAAAABiw/t3SoNXRNa1k/photo.jpg?sz=128", "display_name": "vishal chouksey", "user_type": "registered", "user_id": 6944193, "reputation": 6, "link": "http://stackoverflow.com/users/6944193/vishal-chouksey"}, "score": 1, "creation_date": 1477136127, "last_edit_date": 1477144251, "last_activity_date": 1477144251, "question_id": 40191650, "view_count": 26, "is_answered": false, "answer_count": 0, "link": "http://stackoverflow.com/questions/40191650/getting-error-keyerror-retweeted-status-while-reading-nested-json-document"}, "40113979": {"tags": ["python", "pandas"], "question_id": 40113979, "title": "Sorting on multiple levels in pandas pivot table while preserving subtotals", "view_count": 25, "link": "http://stackoverflow.com/questions/40113979/sorting-on-multiple-levels-in-pandas-pivot-table-while-preserving-subtotals", "owner": {"profile_image": "https://www.gravatar.com/avatar/2289171046a92ea617a3baf5ddc7d99d?s=128&d=identicon&r=PG&f=1", "display_name": "user3313622", "user_type": "registered", "user_id": 3313622, "reputation": 1, "link": "http://stackoverflow.com/users/3313622/user3313622"}, "score": 0, "is_answered": false, "creation_date": 1476809765, "answer_count": 0, "last_activity_date": 1476809765}, "40073279": {"tags": ["python", "pandas", "join", "time-series"], "title": "Cross join time series dataset applying asof criteria on time while limiting number of rows", "owner": {"profile_image": "https://www.gravatar.com/avatar/1e63fe120318adc5fb902d3905f23926?s=128&d=identicon&r=PG&f=1", "display_name": "Rahul", "user_type": "registered", "accept_rate": 0, "user_id": 3978628, "reputation": 11, "link": "http://stackoverflow.com/users/3978628/rahul"}, "score": 0, "creation_date": 1476639237, "last_edit_date": 1476640525, "last_activity_date": 1476640525, "question_id": 40073279, "view_count": 24, "is_answered": false, "answer_count": 0, "link": "http://stackoverflow.com/questions/40073279/cross-join-time-series-dataset-applying-asof-criteria-on-time-while-limiting-num"}, "40079155": {"tags": ["python", "pandas", "matplotlib"], "title": "matplotlib gives a ValueError: could not convert string to float:", "owner": {"profile_image": "https://www.gravatar.com/avatar/3470cfd0496d3f7c5f0c009b4045b4ac?s=128&d=identicon&r=PG", "display_name": "Siddharth Ram", "user_type": "registered", "accept_rate": 59, "user_id": 40661, "reputation": 181, "link": "http://stackoverflow.com/users/40661/siddharth-ram"}, "score": 0, "creation_date": 1476682736, "last_edit_date": 1476685640, "last_activity_date": 1476685640, "question_id": 40079155, "view_count": 29, "is_answered": false, "answer_count": 0, "link": "http://stackoverflow.com/questions/40079155/matplotlib-gives-a-valueerror-could-not-convert-string-to-float"}, "40209731": {"tags": ["python", "python-2.7", "pandas", "pandas-datareader"], "question_id": 40209731, "title": "Pandas DF to Oracle DB", "view_count": 15, "link": "http://stackoverflow.com/questions/40209731/pandas-df-to-oracle-db", "owner": {"profile_image": "https://www.gravatar.com/avatar/ca3ba88621ca73c0ae3b88b8d194fb3e?s=128&d=identicon&r=PG&f=1", "display_name": "Raj", "user_type": "registered", "user_id": 6942678, "reputation": 18, "link": "http://stackoverflow.com/users/6942678/raj"}, "score": 0, "is_answered": false, "creation_date": 1477274354, "answer_count": 0, "last_activity_date": 1477274354}, "40196682": {"tags": ["python", "pandas", "dataframe"], "question_id": 40196682, "title": "How to merge time series data frames in Pandas with asymmetric data?", "view_count": 26, "link": "http://stackoverflow.com/questions/40196682/how-to-merge-time-series-data-frames-in-pandas-with-asymmetric-data", "owner": {"profile_image": "https://i.stack.imgur.com/arHdQ.png?s=128&g=1", "display_name": "alphaleonis", "user_type": "registered", "accept_rate": 56, "user_id": 3450793, "reputation": 140, "link": "http://stackoverflow.com/users/3450793/alphaleonis"}, "score": 0, "is_answered": false, "creation_date": 1477167767, "answer_count": 0, "last_activity_date": 1477167767}, "40093774": {"tags": ["python", "python-3.x", "csv", "pandas"], "question_id": 40093774, "title": "Merge 2 data streams into 1 after using pandas", "view_count": 22, "link": "http://stackoverflow.com/questions/40093774/merge-2-data-streams-into-1-after-using-pandas", "owner": {"profile_image": "https://www.gravatar.com/avatar/0a134da06540ea285f5f4f90ea5117a3?s=128&d=identicon&r=PG&f=1", "display_name": "r0xette", "user_type": "registered", "accept_rate": 70, "user_id": 6646696, "reputation": 56, "link": "http://stackoverflow.com/users/6646696/r0xette"}, "score": 0, "is_answered": false, "creation_date": 1476730964, "answer_count": 0, "last_activity_date": 1476730964}, "40180815": {"tags": ["python", "pandas", "plotly"], "title": "X Axis label is wrong when plotting a Time Series with Plotly and Pandas", "owner": {"profile_image": "https://www.gravatar.com/avatar/d580a45da7b4b71e03df3e09a3abb7a8?s=128&d=identicon&r=PG&f=1", "display_name": "IceS2", "user_type": "registered", "user_id": 6146613, "reputation": 1, "link": "http://stackoverflow.com/users/6146613/ices2"}, "score": -4, "creation_date": 1477065002, "last_edit_date": 1477074482, "last_activity_date": 1477074482, "question_id": 40180815, "view_count": 23, "is_answered": false, "answer_count": 0, "link": "http://stackoverflow.com/questions/40180815/x-axis-label-is-wrong-when-plotting-a-time-series-with-plotly-and-pandas"}, "40069001": {"tags": ["python", "pandas", "plot", "ggplot2", "python-ggplot"], "title": "Pandas and GGPlot &#39;Could not compare [__index__] with block values&#39;, even after df.fillna(0)", "owner": {"profile_image": "https://www.gravatar.com/avatar/09530ed6bcc0b7e3331a20d3bb5c0ddc?s=128&d=identicon&r=PG&f=1", "display_name": "DaveTheAl", "user_type": "registered", "accept_rate": 80, "user_id": 3262787, "reputation": 47, "link": "http://stackoverflow.com/users/3262787/davetheal"}, "score": 0, "creation_date": 1476611658, "last_edit_date": 1476621907, "last_activity_date": 1476621907, "question_id": 40069001, "view_count": 13, "is_answered": false, "answer_count": 0, "link": "http://stackoverflow.com/questions/40069001/pandas-and-ggplot-could-not-compare-index-with-block-values-even-after"}, "40256338": {"tags": ["python", "pandas", "dataframe"], "title": "Calculating Average True Range (ATR) on OHLC data with Python", "owner": {"profile_image": "https://www.gravatar.com/avatar/c502e5e9d12ea37bf80ed84b6d049ca1?s=128&d=identicon&r=PG", "display_name": "cardycakes", "user_type": "registered", "accept_rate": 65, "user_id": 1214212, "reputation": 78, "link": "http://stackoverflow.com/users/1214212/cardycakes"}, "score": 0, "creation_date": 1477467432, "last_edit_date": 1477473913, "last_activity_date": 1477473913, "question_id": 40256338, "view_count": 26, "is_answered": false, "answer_count": 0, "link": "http://stackoverflow.com/questions/40256338/calculating-average-true-range-atr-on-ohlc-data-with-python"}, "40323411": {"tags": ["python", "pandas"], "title": "Appending SQLite / MySQL table with Python Pandas column", "owner": {"profile_image": "https://www.gravatar.com/avatar/a790e6ce0929fcd647f0879edbd9ec3d?s=128&d=identicon&r=PG", "display_name": "zadrozny", "user_type": "registered", "accept_rate": 59, "user_id": 1366410, "reputation": 126, "link": "http://stackoverflow.com/users/1366410/zadrozny"}, "score": 1, "creation_date": 1477773254, "last_edit_date": 1477773695, "last_activity_date": 1477773695, "question_id": 40323411, "view_count": 19, "is_answered": false, "answer_count": 0, "link": "http://stackoverflow.com/questions/40323411/appending-sqlite-mysql-table-with-python-pandas-column"}, "40090254": {"tags": ["python", "pandas", "dataframe", "tweepy", "sentiment-analysis"], "question_id": 40090254, "title": "Grouping Tweets by Half-Hour, Hour, and Day in Pandas Dataframe", "view_count": 27, "link": "http://stackoverflow.com/questions/40090254/grouping-tweets-by-half-hour-hour-and-day-in-pandas-dataframe", "owner": {"profile_image": "https://graph.facebook.com/1586536048319909/picture?type=large", "display_name": "Andrew Smith", "user_type": "registered", "user_id": 7002350, "reputation": 7, "link": "http://stackoverflow.com/users/7002350/andrew-smith"}, "score": 0, "is_answered": false, "creation_date": 1476717988, "answer_count": 0, "last_activity_date": 1476717988}, "40343894": {"tags": ["python", "pandas", "py2exe"], "question_id": 40343894, "title": "Python - using py2exe with pandas", "view_count": 14, "link": "http://stackoverflow.com/questions/40343894/python-using-py2exe-with-pandas", "owner": {"profile_image": "https://www.gravatar.com/avatar/cca1a13f23ae7e5328b6a0cc202dfcd0?s=128&d=identicon&r=PG&f=1", "display_name": "beni", "user_type": "registered", "accept_rate": 44, "user_id": 5714113, "reputation": 133, "link": "http://stackoverflow.com/users/5714113/beni"}, "score": 1, "is_answered": false, "creation_date": 1477922993, "answer_count": 0, "last_activity_date": 1477922993}, "40113593": {"tags": ["python", "pandas", "dataframe"], "title": "Dataframe - Sum Arrays in Cell - Memory Issue", "owner": {"profile_image": "https://i.stack.imgur.com/9vvzC.png?s=128&g=1", "display_name": "Tom", "user_type": "registered", "accept_rate": 56, "user_id": 2287458, "reputation": 114, "link": "http://stackoverflow.com/users/2287458/tom"}, "score": 0, "creation_date": 1476808475, "last_edit_date": 1476809833, "last_activity_date": 1476809833, "question_id": 40113593, "view_count": 55, "is_answered": false, "answer_count": 0, "link": "http://stackoverflow.com/questions/40113593/dataframe-sum-arrays-in-cell-memory-issue"}, "40202331": {"tags": ["python", "pandas", "matplotlib"], "question_id": 40202331, "title": "matplotlib and pandas: Add colors to individual plot points with a map", "view_count": 25, "link": "http://stackoverflow.com/questions/40202331/matplotlib-and-pandas-add-colors-to-individual-plot-points-with-a-map", "owner": {"profile_image": "https://www.gravatar.com/avatar/969ae38e873d3915a4600438fb88d36f?s=128&d=identicon&r=PG&f=1", "display_name": "B. Owens", "user_type": "registered", "user_id": 7060136, "reputation": 1, "link": "http://stackoverflow.com/users/7060136/b-owens"}, "score": -1, "is_answered": false, "creation_date": 1477221744, "answer_count": 0, "last_activity_date": 1477221744}, "40352607": {"tags": ["python", "pandas", "data-visualization"], "question_id": 40352607, "title": "Login Time Wheel Python", "view_count": 9, "link": "http://stackoverflow.com/questions/40352607/login-time-wheel-python", "owner": {"profile_image": "https://lh6.googleusercontent.com/-HaaAI166T-8/AAAAAAAAAAI/AAAAAAAALjI/GJMj2s8Y100/photo.jpg?sz=128", "display_name": "johnnyb", "user_type": "registered", "user_id": 6916973, "reputation": 25, "link": "http://stackoverflow.com/users/6916973/johnnyb"}, "score": 1, "is_answered": false, "creation_date": 1477960975, "answer_count": 0, "last_activity_date": 1477960975}, "40139405": {"tags": ["python", "pandas", "dictionary", "dataframe"], "question_id": 40139405, "title": "building a dataframe from grouped data in pandas", "view_count": 37, "link": "http://stackoverflow.com/questions/40139405/building-a-dataframe-from-grouped-data-in-pandas", "owner": {"profile_image": "https://www.gravatar.com/avatar/035c760ea955c2fd227e16351e51cc1a?s=128&d=identicon&r=PG&f=1", "display_name": "Al_Iskander", "user_type": "registered", "accept_rate": 80, "user_id": 6306448, "reputation": 204, "link": "http://stackoverflow.com/users/6306448/al-iskander"}, "score": 2, "is_answered": false, "creation_date": 1476903253, "answer_count": 0, "last_activity_date": 1476903253}, "40120931": {"tags": ["python", "pandas", "pyodbc"], "question_id": 40120931, "title": "pandas list cursor error", "view_count": 20, "link": "http://stackoverflow.com/questions/40120931/pandas-list-cursor-error", "owner": {"profile_image": "https://www.gravatar.com/avatar/976dd4928e035a6d837ad42e410b2993?s=128&d=identicon&r=PG&f=1", "display_name": "BLang", "user_type": "registered", "user_id": 6855437, "reputation": 82, "link": "http://stackoverflow.com/users/6855437/blang"}, "score": 0, "is_answered": false, "creation_date": 1476842974, "answer_count": 0, "last_activity_date": 1476842974}, "40160101": {"tags": ["python", "csv", "pandas", "dataframe", "max"], "title": "pandas.DataFrame.max() command does not return correct values", "owner": {"profile_image": "https://www.gravatar.com/avatar/5caee95acc198980d5f476ed50fe7e73?s=128&d=identicon&r=PG&f=1", "display_name": "Andreuccio", "user_type": "registered", "accept_rate": 61, "user_id": 6071128, "reputation": 65, "link": "http://stackoverflow.com/users/6071128/andreuccio"}, "score": -1, "creation_date": 1476982006, "last_edit_date": 1476982856, "last_activity_date": 1476982856, "question_id": 40160101, "view_count": 27, "is_answered": false, "answer_count": 0, "link": "http://stackoverflow.com/questions/40160101/pandas-dataframe-max-command-does-not-return-correct-values"}, "40213095": {"tags": ["python", "pandas"], "title": "what is a verifiable example of how to trigger a `is_copy` flag?", "owner": {"profile_image": "https://i.stack.imgur.com/cZOEs.jpg?s=128&g=1", "display_name": "piRSquared", "user_type": "registered", "accept_rate": 96, "user_id": 2336654, "reputation": 30209, "link": "http://stackoverflow.com/users/2336654/pirsquared"}, "score": 2, "creation_date": 1477294972, "last_edit_date": 1477295466, "last_activity_date": 1477295466, "question_id": 40213095, "view_count": 32, "is_answered": false, "answer_count": 0, "link": "http://stackoverflow.com/questions/40213095/what-is-a-verifiable-example-of-how-to-trigger-a-is-copy-flag"}, "40140813": {"tags": ["python", "pandas", "visualization", "data-visualization", "jupyter"], "title": "Brunel API not read dataframe?", "owner": {"profile_image": "https://www.gravatar.com/avatar/893898102c9c21094a0c31d7d4258a42?s=128&d=identicon&r=PG&f=1", "display_name": "Farman Ali", "user_type": "registered", "user_id": 4863152, "reputation": 1, "link": "http://stackoverflow.com/users/4863152/farman-ali"}, "score": 0, "creation_date": 1476908431, "last_edit_date": 1476947349, "last_activity_date": 1476947349, "question_id": 40140813, "view_count": 13, "is_answered": false, "answer_count": 0, "link": "http://stackoverflow.com/questions/40140813/brunel-api-not-read-dataframe"}, "40236907": {"tags": ["python", "pandas", "duplicates"], "title": "A special case of duplicates", "owner": {"profile_image": "https://www.gravatar.com/avatar/78be80f1e81829416b25918b1380d8c3?s=128&d=identicon&r=PG", "display_name": "akotronis", "user_type": "registered", "user_id": 6650391, "reputation": 11, "link": "http://stackoverflow.com/users/6650391/akotronis"}, "score": 2, "creation_date": 1477389506, "last_edit_date": 1477467452, "last_activity_date": 1477467452, "question_id": 40236907, "view_count": 39, "is_answered": false, "answer_count": 0, "link": "http://stackoverflow.com/questions/40236907/a-special-case-of-duplicates"}, "40084589": {"tags": ["python", "pandas"], "title": "Setting low_memory to false while reading a mixed dtype 2.5GB csv file using Pandas is not working", "owner": {"profile_image": "https://www.gravatar.com/avatar/fd934e39469f78fbf51808f698c75917?s=128&d=identicon&r=PG&f=1", "display_name": "ganesh kumar", "user_type": "registered", "user_id": 6559048, "reputation": 46, "link": "http://stackoverflow.com/users/6559048/ganesh-kumar"}, "score": 0, "creation_date": 1476701770, "last_edit_date": 1476701869, "last_activity_date": 1476890856, "question_id": 40084589, "view_count": 22, "is_answered": false, "answer_count": 0, "link": "http://stackoverflow.com/questions/40084589/setting-low-memory-to-false-while-reading-a-mixed-dtype-2-5gb-csv-file-using-pan"}, "40079982": {"tags": ["python", "csv", "pandas"], "title": "get_dummies() throws Memory Error", "owner": {"profile_image": "https://lh6.googleusercontent.com/-EinHHo7KtZY/AAAAAAAAAAI/AAAAAAAAARc/NczRdYxLEOU/photo.jpg?sz=128", "display_name": "Mukesh Kumar Mishra", "user_type": "registered", "accept_rate": 38, "user_id": 6354721, "reputation": 28, "link": "http://stackoverflow.com/users/6354721/mukesh-kumar-mishra"}, "score": 0, "creation_date": 1476686542, "last_edit_date": 1476688289, "last_activity_date": 1476688289, "question_id": 40079982, "view_count": 23, "is_answered": false, "answer_count": 0, "link": "http://stackoverflow.com/questions/40079982/get-dummies-throws-memory-error"}, "40079794": {"tags": ["python", "pandas", "numpy"], "title": "How to change the data types of a column in Pandas when read_csv()", "owner": {"profile_image": "https://www.gravatar.com/avatar/c8057af8accc3d51136e21c96275e054?s=128&d=identicon&r=PG&f=1", "display_name": "orage mittai", "user_type": "registered", "user_id": 7029378, "reputation": 1, "link": "http://stackoverflow.com/users/7029378/orage-mittai"}, "score": 0, "creation_date": 1476685734, "last_edit_date": 1476690864, "last_activity_date": 1476690864, "question_id": 40079794, "view_count": 38, "is_answered": false, "answer_count": 0, "link": "http://stackoverflow.com/questions/40079794/how-to-change-the-data-types-of-a-column-in-pandas-when-read-csv"}, "40083816": {"tags": ["python", "regex", "pandas"], "question_id": 40083816, "title": "trimming a pandas column with regex", "view_count": 28, "link": "http://stackoverflow.com/questions/40083816/trimming-a-pandas-column-with-regex", "owner": {"profile_image": "https://graph.facebook.com/1156558524362599/picture?type=large", "display_name": "Andrei Cozma", "user_type": "registered", "accept_rate": 0, "user_id": 6083319, "reputation": 27, "link": "http://stackoverflow.com/users/6083319/andrei-cozma"}, "score": -1, "is_answered": false, "creation_date": 1476699564, "answer_count": 0, "last_activity_date": 1476699564}, "40117874": {"tags": ["python", "pandas"], "question_id": 40117874, "title": "accelerating the data generation process", "view_count": 26, "link": "http://stackoverflow.com/questions/40117874/accelerating-the-data-generation-process", "owner": {"profile_image": "https://www.gravatar.com/avatar/e30f4274dc6fa3ade80d0685a72fd90a?s=128&d=identicon&r=PG&f=1", "display_name": "Vacassal Alsk", "user_type": "registered", "accept_rate": 26, "user_id": 5982950, "reputation": 72, "link": "http://stackoverflow.com/users/5982950/vacassal-alsk"}, "score": -1, "is_answered": false, "creation_date": 1476823953, "answer_count": 0, "last_activity_date": 1476823953}, "40080019": {"tags": ["python", "pandas"], "question_id": 40080019, "title": "deleting pandas dataframe column", "view_count": 26, "link": "http://stackoverflow.com/questions/40080019/deleting-pandas-dataframe-column", "owner": {"profile_image": "https://graph.facebook.com/1156558524362599/picture?type=large", "display_name": "Andrei Cozma", "user_type": "registered", "accept_rate": 0, "user_id": 6083319, "reputation": 27, "link": "http://stackoverflow.com/users/6083319/andrei-cozma"}, "score": 0, "is_answered": false, "creation_date": 1476686698, "answer_count": 0, "last_activity_date": 1476686698}, "40114807": {"tags": ["python", "pandas"], "title": "pandas updating column value using isin and loc", "owner": {"profile_image": "https://www.gravatar.com/avatar/f50e6f719b4365119839a2292501deb5?s=128&d=identicon&r=PG&f=1", "display_name": "SKU_MIG", "user_type": "registered", "user_id": 5769068, "reputation": 1, "link": "http://stackoverflow.com/users/5769068/sku-mig"}, "score": 0, "creation_date": 1476812779, "last_edit_date": 1476815220, "last_activity_date": 1476815220, "question_id": 40114807, "view_count": 41, "is_answered": false, "answer_count": 0, "link": "http://stackoverflow.com/questions/40114807/pandas-updating-column-value-using-isin-and-loc"}, "40235384": {"tags": ["python", "pandas"], "question_id": 40235384, "title": "Pandas dataframe series has bengali values. How to include it in a bar chart xticks?", "view_count": 18, "link": "http://stackoverflow.com/questions/40235384/pandas-dataframe-series-has-bengali-values-how-to-include-it-in-a-bar-chart-xti", "owner": {"profile_image": "https://www.gravatar.com/avatar/a9cfe2a498275758f99d7db61ceb2ad2?s=128&d=identicon&r=PG&f=1", "display_name": "Mainul Islam", "user_type": "registered", "user_id": 6596015, "reputation": 14, "link": "http://stackoverflow.com/users/6596015/mainul-islam"}, "score": 0, "is_answered": false, "creation_date": 1477385159, "answer_count": 0, "last_activity_date": 1477385159}, "40119416": {"tags": ["python", "pandas", "binning"], "question_id": 40119416, "title": "Pandas - Loc w/categories", "view_count": 30, "link": "http://stackoverflow.com/questions/40119416/pandas-loc-w-categories", "owner": {"profile_image": "https://www.gravatar.com/avatar/c7b8e621975dc850fc4cd13bce72949f?s=128&d=identicon&r=PG&f=1", "display_name": "econgineer", "user_type": "registered", "accept_rate": 67, "user_id": 3430943, "reputation": 92, "link": "http://stackoverflow.com/users/3430943/econgineer"}, "score": 2, "is_answered": false, "creation_date": 1476831485, "answer_count": 0, "last_activity_date": 1476831485}, "40244094": {"tags": ["python", "pandas", "dataframe", "tuples"], "title": "Python Pandas -- Determine if Values in Column 0 Are Repeated in Each Subsequent Column", "owner": {"profile_image": "https://www.gravatar.com/avatar/7948014e3240c21b3c2be629c268fd20?s=128&d=identicon&r=PG&f=1", "display_name": "OnlyDean", "user_type": "registered", "accept_rate": 73, "user_id": 3285817, "reputation": 144, "link": "http://stackoverflow.com/users/3285817/onlydean"}, "score": 0, "creation_date": 1477409712, "last_edit_date": 1477429418, "last_activity_date": 1477429418, "question_id": 40244094, "view_count": 36, "is_answered": false, "answer_count": 0, "link": "http://stackoverflow.com/questions/40244094/python-pandas-determine-if-values-in-column-0-are-repeated-in-each-subsequent"}, "40114305": {"tags": ["python", "multithreading", "pandas", "dataframe", "parallel-processing"], "question_id": 40114305, "title": "parallel processing with dataframes python", "view_count": 19, "link": "http://stackoverflow.com/questions/40114305/parallel-processing-with-dataframes-python", "owner": {"profile_image": "https://www.gravatar.com/avatar/88f06daddc0d94f9e85e71b20c294cf3?s=128&d=identicon&r=PG&f=1", "display_name": "AMisra", "user_type": "registered", "accept_rate": 81, "user_id": 3974476, "reputation": 288, "link": "http://stackoverflow.com/users/3974476/amisra"}, "score": 0, "is_answered": false, "creation_date": 1476810938, "answer_count": 0, "last_activity_date": 1476810938}, "40105090": {"tags": ["python", "pandas"], "title": "Find pre/post-decessor in pandas for each group", "owner": {"profile_image": "https://www.gravatar.com/avatar/ca2290acd27712398ff5bf1d469129dd?s=128&d=identicon&r=PG", "display_name": "Quickbeam2k1", "user_type": "registered", "accept_rate": 64, "user_id": 5152563, "reputation": 225, "link": "http://stackoverflow.com/users/5152563/quickbeam2k1"}, "score": 2, "creation_date": 1476784543, "last_edit_date": 1476805831, "last_activity_date": 1476805831, "question_id": 40105090, "view_count": 41, "is_answered": false, "answer_count": 0, "link": "http://stackoverflow.com/questions/40105090/find-pre-post-decessor-in-pandas-for-each-group"}, "40328324": {"tags": ["python", "database", "pandas", "ssh-tunnel"], "question_id": 40328324, "title": "sshtunnel not working in when used in a function", "view_count": 10, "link": "http://stackoverflow.com/questions/40328324/sshtunnel-not-working-in-when-used-in-a-function", "owner": {"profile_image": "https://lh5.googleusercontent.com/-pyay1chvZbI/AAAAAAAAAAI/AAAAAAAABPg/UB_TG45HWL8/photo.jpg?sz=128", "display_name": "Lucas Neo", "user_type": "registered", "user_id": 4804043, "reputation": 18, "link": "http://stackoverflow.com/users/4804043/lucas-neo"}, "score": 0, "is_answered": false, "creation_date": 1477824866, "answer_count": 0, "last_activity_date": 1477824866}, "40340873": {"tags": ["python", "pandas", "dataframe"], "title": "Python count the frequency value - create data structure", "owner": {"profile_image": "https://www.gravatar.com/avatar/a2078d1fa9720387da7812214c012392?s=128&d=identicon&r=PG", "display_name": "phoenix37", "user_type": "registered", "accept_rate": 80, "user_id": 4406224, "reputation": 63, "link": "http://stackoverflow.com/users/4406224/phoenix37"}, "score": -1, "creation_date": 1477911784, "last_edit_date": 1477916391, "last_activity_date": 1477916391, "question_id": 40340873, "view_count": 29, "is_answered": false, "answer_count": 0, "link": "http://stackoverflow.com/questions/40340873/python-count-the-frequency-value-create-data-structure"}, "40201868": {"tags": ["python", "pandas", "apache-spark", "dstream"], "question_id": 40201868, "title": "Spark Streaming: From DStream to Pandas Dataframe", "view_count": 32, "link": "http://stackoverflow.com/questions/40201868/spark-streaming-from-dstream-to-pandas-dataframe", "owner": {"profile_image": "https://www.gravatar.com/avatar/27c05582a5c3ad4d8eea8f37777b69dd?s=128&d=identicon&r=PG&f=1", "display_name": "HappyCane", "user_type": "registered", "accept_rate": 71, "user_id": 4258415, "reputation": 76, "link": "http://stackoverflow.com/users/4258415/happycane"}, "score": 1, "is_answered": false, "creation_date": 1477218158, "answer_count": 0, "last_activity_date": 1477218158}, "40102285": {"tags": ["python", "csv", "pandas", "pickle", "python-multiprocessing"], "question_id": 40102285, "title": "Pickling error in passing Pandas DataFrame to method call in multi processing", "view_count": 28, "link": "http://stackoverflow.com/questions/40102285/pickling-error-in-passing-pandas-dataframe-to-method-call-in-multi-processing", "owner": {"profile_image": "https://www.gravatar.com/avatar/b61239d14a111f13f5ed5a51ce4407bb?s=128&d=identicon&r=PG&f=1", "display_name": "Debasish Kanhar", "user_type": "registered", "accept_rate": 40, "user_id": 3763498, "reputation": 72, "link": "http://stackoverflow.com/users/3763498/debasish-kanhar"}, "score": 1, "is_answered": false, "creation_date": 1476776315, "answer_count": 0, "last_activity_date": 1476776315}, "40351118": {"tags": ["python", "pandas", "scipy", "statistics", "entropy"], "title": "How is scipy.stats.entropy calculated?", "owner": {"profile_image": "https://lh4.googleusercontent.com/-fC0c6sCXfX0/AAAAAAAAAAI/AAAAAAAAAFg/IGAw-w88-6c/photo.jpg?sz=128", "display_name": "WillacyMe", "user_type": "registered", "accept_rate": 44, "user_id": 4459665, "reputation": 58, "link": "http://stackoverflow.com/users/4459665/willacyme"}, "score": 0, "creation_date": 1477950591, "last_edit_date": 1477967186, "last_activity_date": 1477967186, "question_id": 40351118, "view_count": 21, "is_answered": false, "answer_count": 0, "link": "http://stackoverflow.com/questions/40351118/how-is-scipy-stats-entropy-calculated"}, "40101519": {"tags": ["python", "pandas", "data-analysis", "python-ggplot"], "title": "Plotting event density in Python with ggplot and pandas", "owner": {"profile_image": "https://www.gravatar.com/avatar/651d26fd42bc3ebd927fa79c3e808c51?s=128&d=identicon&r=PG", "display_name": "MasterScrat", "user_type": "registered", "accept_rate": 90, "user_id": 318557, "reputation": 1451, "link": "http://stackoverflow.com/users/318557/masterscrat"}, "score": 2, "creation_date": 1476773787, "last_edit_date": 1476780177, "last_activity_date": 1476780177, "question_id": 40101519, "view_count": 32, "is_answered": false, "answer_count": 0, "link": "http://stackoverflow.com/questions/40101519/plotting-event-density-in-python-with-ggplot-and-pandas"}, "40211090": {"tags": ["python", "pandas"], "title": "Computing Aggregated Stats on Pandas", "owner": {"profile_image": "https://www.gravatar.com/avatar/e295ae8fb68f97c00b8b61a2de8d9036?s=128&d=identicon&r=PG&f=1", "display_name": "user3635284", "user_type": "registered", "accept_rate": 75, "user_id": 3635284, "reputation": 30, "link": "http://stackoverflow.com/users/3635284/user3635284"}, "score": -1, "creation_date": 1477285852, "last_edit_date": 1477295126, "last_activity_date": 1477295126, "question_id": 40211090, "view_count": 20, "is_answered": false, "answer_count": 0, "link": "http://stackoverflow.com/questions/40211090/computing-aggregated-stats-on-pandas"}, "40180371": {"tags": ["python", "csv", "pandas", "dictionary", "dataframe"], "title": "Dataframe with many punctuation marks to csv using python3", "owner": {"profile_image": "https://www.gravatar.com/avatar/5fb7a01316061395067ec7650a991535?s=128&d=identicon&r=PG", "display_name": "user2246905", "user_type": "registered", "accept_rate": 86, "user_id": 2246905, "reputation": 392, "link": "http://stackoverflow.com/users/2246905/user2246905"}, "score": 0, "creation_date": 1477063516, "last_edit_date": 1477110897, "last_activity_date": 1477110897, "question_id": 40180371, "view_count": 12, "is_answered": false, "answer_count": 0, "link": "http://stackoverflow.com/questions/40180371/dataframe-with-many-punctuation-marks-to-csv-using-python3"}, "32383381": {"tags": ["python", "pandas", "scikit-learn"], "title": "Python sklearn preprocessing package returns error: ValueError: invalid literal for float()", "owner": {"profile_image": "https://www.gravatar.com/avatar/96059824f2f3da358b88e0550749610d?s=128&d=identicon&r=PG&f=1", "display_name": "ahajib", "user_type": "registered", "accept_rate": 91, "user_id": 2827771, "reputation": 1229, "link": "http://stackoverflow.com/users/2827771/ahajib"}, "score": 0, "creation_date": 1441306489, "last_edit_date": 1476658168, "last_activity_date": 1476658168, "question_id": 32383381, "view_count": 179, "is_answered": false, "answer_count": 0, "link": "http://stackoverflow.com/questions/32383381/python-sklearn-preprocessing-package-returns-error-valueerror-invalid-literal"}, "40352406": {"tags": ["python", "python-3.x", "pandas", "table", "merge"], "question_id": 40352406, "title": "How to do context dependent data frame merge in python?", "view_count": 11, "link": "http://stackoverflow.com/questions/40352406/how-to-do-context-dependent-data-frame-merge-in-python", "owner": {"profile_image": "https://www.gravatar.com/avatar/c20ab6d6a6597a7be342a662a0d42e6b?s=128&d=identicon&r=PG&f=1", "display_name": "everestial007", "user_type": "registered", "user_id": 6346698, "reputation": 28, "link": "http://stackoverflow.com/users/6346698/everestial007"}, "score": 0, "is_answered": false, "creation_date": 1477959303, "answer_count": 0, "last_activity_date": 1477959303}, "40241047": {"tags": ["python", "pandas", "numpy"], "question_id": 40241047, "title": "Matrix vector product of panel and dataframe without loop", "view_count": 39, "link": "http://stackoverflow.com/questions/40241047/matrix-vector-product-of-panel-and-dataframe-without-loop", "owner": {"profile_image": "https://www.gravatar.com/avatar/ae7b79be8bafc0f649589174bb15eefe?s=128&d=identicon&r=PG&f=1", "display_name": "NewbiZ", "user_type": "registered", "accept_rate": 100, "user_id": 158049, "reputation": 1347, "link": "http://stackoverflow.com/users/158049/newbiz"}, "score": 3, "is_answered": false, "creation_date": 1477401415, "answer_count": 0, "last_activity_date": 1477407962}, "40279387": {"tags": ["python", "json", "pandas", "dictionary"], "question_id": 40279387, "title": "Pandas - improving memory usage when loading dumped json in column as dictionaries", "view_count": 16, "link": "http://stackoverflow.com/questions/40279387/pandas-improving-memory-usage-when-loading-dumped-json-in-column-as-dictionari", "owner": {"profile_image": "https://www.gravatar.com/avatar/462a44debc70083c5834cefce94ab000?s=128&d=identicon&r=PG&f=1", "display_name": "Yaniv Meller", "user_type": "registered", "user_id": 6688002, "reputation": 11, "link": "http://stackoverflow.com/users/6688002/yaniv-meller"}, "score": 2, "is_answered": false, "creation_date": 1477555676, "answer_count": 0, "last_activity_date": 1477555676}, "40353695": {"tags": ["python", "pandas", "time-series", "statsmodels", "google-prediction"], "question_id": 40353695, "title": "Prediction of Stock Prices using ARIMA", "view_count": 12, "link": "http://stackoverflow.com/questions/40353695/prediction-of-stock-prices-using-arima", "owner": {"profile_image": "https://www.gravatar.com/avatar/92a8ccd79a3834fe17322de657279477?s=128&d=identicon&r=PG&f=1", "display_name": "Beginner1111", "user_type": "registered", "accept_rate": 75, "user_id": 5400974, "reputation": 9, "link": "http://stackoverflow.com/users/5400974/beginner1111"}, "score": 0, "is_answered": false, "creation_date": 1477970524, "answer_count": 0, "last_activity_date": 1477970524}, "40095906": {"tags": ["python", "pandas", "dataframe", "time-series", "concat"], "question_id": 40095906, "title": "Pandas concat : Incorrect total length after dataframes are concatenated", "view_count": 34, "link": "http://stackoverflow.com/questions/40095906/pandas-concat-incorrect-total-length-after-dataframes-are-concatenated", "owner": {"profile_image": "https://www.gravatar.com/avatar/badfc19810f8531e64af122c1fc23cbf?s=128&d=identicon&r=PG&f=1", "display_name": "wi3o", "user_type": "registered", "accept_rate": 33, "user_id": 3483133, "reputation": 87, "link": "http://stackoverflow.com/users/3483133/wi3o"}, "score": 0, "is_answered": false, "creation_date": 1476739572, "answer_count": 0, "last_activity_date": 1476739572}, "40070051": {"tags": ["python", "python-3.x", "pandas", "anaconda"], "question_id": 40070051, "title": "How to import Pandas library in Python?", "view_count": 46, "link": "http://stackoverflow.com/questions/40070051/how-to-import-pandas-library-in-python", "owner": {"profile_image": "https://www.gravatar.com/avatar/5dc7bb4fea9f9fa6cb5f4536b0c78120?s=128&d=identicon&r=PG&f=1", "display_name": "Stanislav Jir&#225;k", "user_type": "registered", "accept_rate": 83, "user_id": 5021612, "reputation": 52, "link": "http://stackoverflow.com/users/5021612/stanislav-jir%c3%a1k"}, "score": -1, "is_answered": false, "creation_date": 1476619498, "answer_count": 0, "last_activity_date": 1476619498}, "40157608": {"tags": ["python", "pandas"], "title": "Pandas date overlap", "owner": {"profile_image": "https://www.gravatar.com/avatar/baa7795cd5288fa3329c9c394ca5870d?s=128&d=identicon&r=PG&f=1", "display_name": "bigdata", "user_type": "registered", "user_id": 7044475, "reputation": 16, "link": "http://stackoverflow.com/users/7044475/bigdata"}, "score": 0, "creation_date": 1476974565, "last_edit_date": 1477149793, "last_activity_date": 1477149793, "question_id": 40157608, "view_count": 31, "is_answered": false, "answer_count": 0, "link": "http://stackoverflow.com/questions/40157608/pandas-date-overlap"}, "40142766": {"tags": ["python", "json", "python-3.x", "pandas", "python-requests"], "question_id": 40142766, "title": "How to remove elements from a nested json with pandas?", "view_count": 31, "link": "http://stackoverflow.com/questions/40142766/how-to-remove-elements-from-a-nested-json-with-pandas", "owner": {"profile_image": "https://www.gravatar.com/avatar/b374a0395b39b278373c21b5c6840d1b?s=128&d=identicon&r=PG&f=1", "display_name": "john doe", "user_type": "registered", "accept_rate": 65, "user_id": 4114372, "reputation": 51, "link": "http://stackoverflow.com/users/4114372/john-doe"}, "score": 0, "is_answered": false, "creation_date": 1476917449, "answer_count": 0, "last_activity_date": 1476917449}, "40212401": {"tags": ["python", "python-3.x", "pandas"], "title": "What is the equivalent for Iterrows in Python 3.5", "owner": {"profile_image": "https://www.gravatar.com/avatar/7880467173d728298d13a46f0b77da17?s=128&d=identicon&r=PG&f=1", "display_name": "Praveen Kumar B", "user_type": "registered", "user_id": 4011194, "reputation": 1, "link": "http://stackoverflow.com/users/4011194/praveen-kumar-b"}, "score": 0, "creation_date": 1477292385, "last_edit_date": 1477295893, "last_activity_date": 1477295901, "question_id": 40212401, "view_count": 48, "is_answered": false, "answer_count": 0, "link": "http://stackoverflow.com/questions/40212401/what-is-the-equivalent-for-iterrows-in-python-3-5"}, "40099762": {"tags": ["python", "pandas", "genetic-algorithm"], "question_id": 40099762, "title": "Individual/Population selection in Genetic Algorithm using Pandas", "view_count": 14, "link": "http://stackoverflow.com/questions/40099762/individual-population-selection-in-genetic-algorithm-using-pandas", "owner": {"profile_image": "https://www.gravatar.com/avatar/35367681619acaad6ef7c11b2f145f44?s=128&d=identicon&r=PG&f=1", "display_name": "Settler7", "user_type": "registered", "accept_rate": 93, "user_id": 5679881, "reputation": 65, "link": "http://stackoverflow.com/users/5679881/settler7"}, "score": 0, "is_answered": false, "creation_date": 1476766252, "answer_count": 0, "last_activity_date": 1476766252}, "40137140": {"tags": ["python", "pandas", "machine-learning", "scikit-learn", "data-science"], "question_id": 40137140, "title": "Apply different estimators on data points depending on which features are present", "view_count": 20, "link": "http://stackoverflow.com/questions/40137140/apply-different-estimators-on-data-points-depending-on-which-features-are-presen", "owner": {"profile_image": "https://www.gravatar.com/avatar/b3e754c2ec8d85c530645967ee25d230?s=128&d=identicon&r=PG&f=1", "display_name": "Hargen.Hans", "user_type": "registered", "accept_rate": 75, "user_id": 6268892, "reputation": 68, "link": "http://stackoverflow.com/users/6268892/hargen-hans"}, "score": 1, "is_answered": false, "creation_date": 1476895278, "answer_count": 0, "last_activity_date": 1476895278}, "40142265": {"tags": ["python", "pandas", "parallel-processing"], "question_id": 40142265, "title": "pandas parallel do not stop", "view_count": 14, "link": "http://stackoverflow.com/questions/40142265/pandas-parallel-do-not-stop", "owner": {"profile_image": "https://www.gravatar.com/avatar/c8930dd2a749b59e6e43632029d11997?s=128&d=identicon&r=PG&f=1", "display_name": "JOHN", "user_type": "registered", "accept_rate": 100, "user_id": 3885985, "reputation": 22, "link": "http://stackoverflow.com/users/3885985/john"}, "score": 0, "is_answered": false, "creation_date": 1476914578, "answer_count": 0, "last_activity_date": 1476914578}, "37516730": {"tags": ["python", "pandas", "back-testing"], "title": "Backtesting with Data", "owner": {"profile_image": "https://www.gravatar.com/avatar/d05487ad5b221536a1702b4e3ff86bd1?s=128&d=identicon&r=PG&f=1", "display_name": "Alt182", "user_type": "registered", "accept_rate": 75, "user_id": 4157564, "reputation": 88, "link": "http://stackoverflow.com/users/4157564/alt182"}, "score": 0, "creation_date": 1464573816, "last_edit_date": 1464650924, "last_activity_date": 1476804874, "question_id": 37516730, "view_count": 62, "is_answered": false, "answer_count": 0, "link": "http://stackoverflow.com/questions/37516730/backtesting-with-data"}, "40350907": {"tags": ["python", "pandas", "statistics", "data-visualization"], "title": "Login Log Off analysis Python Pandas Timelining", "owner": {"profile_image": "https://lh6.googleusercontent.com/-HaaAI166T-8/AAAAAAAAAAI/AAAAAAAALjI/GJMj2s8Y100/photo.jpg?sz=128", "display_name": "johnnyb", "user_type": "registered", "user_id": 6916973, "reputation": 25, "link": "http://stackoverflow.com/users/6916973/johnnyb"}, "score": 0, "creation_date": 1477949482, "last_edit_date": 1477950076, "last_activity_date": 1477950076, "question_id": 40350907, "view_count": 25, "is_answered": false, "answer_count": 0, "link": "http://stackoverflow.com/questions/40350907/login-log-off-analysis-python-pandas-timelining"}, "40337482": {"tags": ["python", "excel", "pandas"], "question_id": 40337482, "title": "PermissionError: [Errno 13] Permission denied: &#39;pubmed_output&#39; (writing to csv file)", "view_count": 15, "link": "http://stackoverflow.com/questions/40337482/permissionerror-errno-13-permission-denied-pubmed-output-writing-to-csv-f", "owner": {"profile_image": "https://graph.facebook.com/1292837580735777/picture?type=large", "display_name": "Molly Zhao", "user_type": "registered", "accept_rate": 40, "user_id": 6806330, "reputation": 21, "link": "http://stackoverflow.com/users/6806330/molly-zhao"}, "score": -1, "is_answered": false, "creation_date": 1477895186, "answer_count": 0, "last_activity_date": 1477895186}, "40209089": {"tags": ["python", "pandas", "dataframe"], "question_id": 40209089, "title": "ObjectHashTable.get_item (pandas/hashtable.c:13115) error in pandas dataframe; issues in indexing a column", "view_count": 11, "link": "http://stackoverflow.com/questions/40209089/objecthashtable-get-item-pandas-hashtable-c13115-error-in-pandas-dataframe-i", "owner": {"profile_image": "https://i.stack.imgur.com/OVEGI.png?s=128&g=1", "display_name": "mezz", "user_type": "registered", "user_id": 5240245, "reputation": 16, "link": "http://stackoverflow.com/users/5240245/mezz"}, "score": 0, "is_answered": false, "creation_date": 1477267789, "answer_count": 0, "last_activity_date": 1477267789}, "40348099": {"tags": ["python", "pandas", "dataframe", "subset"], "title": "How do I freeze a pandas dataframe column when subsetting the data frame?", "owner": {"profile_image": "https://www.gravatar.com/avatar/5a1b0ecb0e008a6599976f6b34795929?s=128&d=identicon&r=PG&f=1", "display_name": "annieco2929", "user_type": "registered", "user_id": 7032718, "reputation": 6, "link": "http://stackoverflow.com/users/7032718/annieco2929"}, "score": 0, "creation_date": 1477937802, "last_edit_date": 1477938070, "last_activity_date": 1477938070, "question_id": 40348099, "view_count": 18, "is_answered": false, "answer_count": 0, "link": "http://stackoverflow.com/questions/40348099/how-do-i-freeze-a-pandas-dataframe-column-when-subsetting-the-data-frame"}, "40084676": {"tags": ["python", "pandas", "dataframe"], "question_id": 40084676, "title": "Change 1*140 dataframe to 7*20 dataframe in python pandas", "view_count": 41, "link": "http://stackoverflow.com/questions/40084676/change-1140-dataframe-to-720-dataframe-in-python-pandas", "owner": {"profile_image": "https://www.gravatar.com/avatar/7cdee843e31c0b50cf0daec2d228be50?s=128&d=identicon&r=PG", "display_name": "user1829708", "user_type": "registered", "user_id": 1829708, "reputation": 14, "link": "http://stackoverflow.com/users/1829708/user1829708"}, "score": 1, "is_answered": false, "creation_date": 1476702034, "answer_count": 0, "last_activity_date": 1476702034}, "40085447": {"tags": ["python", "pandas"], "question_id": 40085447, "title": "Pandas: compare two dataframe and intersect that", "view_count": 23, "link": "http://stackoverflow.com/questions/40085447/pandas-compare-two-dataframe-and-intersect-that", "owner": {"profile_image": "https://www.gravatar.com/avatar/bbe8da8fb805e0564d583715d6addb74?s=128&d=identicon&r=PG&f=1", "display_name": "Petr Petrov", "user_type": "registered", "accept_rate": 63, "user_id": 6840039, "reputation": 165, "link": "http://stackoverflow.com/users/6840039/petr-petrov"}, "score": -2, "is_answered": false, "creation_date": 1476704401, "answer_count": 0, "last_activity_date": 1476704401}, "40225224": {"tags": ["python", "pandas"], "title": "Python: the pandas dataframe function keep thinking the same dataframe has different dimensions", "owner": {"profile_image": "https://i.stack.imgur.com/rLiLO.jpg?s=128&g=1", "display_name": "alwaysaskingquestions", "user_type": "registered", "accept_rate": 75, "user_id": 5688999, "reputation": 127, "link": "http://stackoverflow.com/users/5688999/alwaysaskingquestions"}, "score": 1, "creation_date": 1477334233, "last_edit_date": 1477420933, "last_activity_date": 1477420933, "question_id": 40225224, "view_count": 23, "is_answered": false, "answer_count": 0, "link": "http://stackoverflow.com/questions/40225224/python-the-pandas-dataframe-function-keep-thinking-the-same-dataframe-has-diffe"}, "40269047": {"tags": ["python", "pandas", "flask"], "question_id": 40269047, "title": "Return excel file from pandas with flask", "view_count": 28, "link": "http://stackoverflow.com/questions/40269047/return-excel-file-from-pandas-with-flask", "owner": {"profile_image": "https://www.gravatar.com/avatar/a9970701b1dfa33fd1932cdc4f852261?s=128&d=identicon&r=PG&f=1", "display_name": "nickpick", "user_type": "registered", "accept_rate": 65, "user_id": 5905642, "reputation": 418, "link": "http://stackoverflow.com/users/5905642/nickpick"}, "score": 0, "is_answered": false, "creation_date": 1477504450, "answer_count": 0, "last_activity_date": 1477504450}, "40274850": {"tags": ["python", "pandas", "web-scraping", "mechanize", "bs4"], "question_id": 40274850, "title": "Python - Using Pandas with a Mechanize and BS4 Response", "view_count": 21, "link": "http://stackoverflow.com/questions/40274850/python-using-pandas-with-a-mechanize-and-bs4-response", "owner": {"profile_image": "https://lh6.googleusercontent.com/-bzaCTO7KNJY/AAAAAAAAAAI/AAAAAAAAAD0/mAH7D5PkkeQ/photo.jpg?sz=128", "display_name": "Sebas Pinto", "user_type": "registered", "user_id": 5873366, "reputation": 13, "link": "http://stackoverflow.com/users/5873366/sebas-pinto"}, "score": 0, "is_answered": false, "creation_date": 1477532942, "answer_count": 0, "last_activity_date": 1477532942}, "40321232": {"tags": ["python", "pandas", "scikit-learn", "dummy-variable", "one-hot-encoding"], "question_id": 40321232, "title": "Handling unknown values for label encoding", "view_count": 47, "link": "http://stackoverflow.com/questions/40321232/handling-unknown-values-for-label-encoding", "owner": {"profile_image": "https://i.stack.imgur.com/31ZTY.jpg?s=128&g=1", "display_name": "Georg Heiler", "user_type": "registered", "accept_rate": 98, "user_id": 2587904, "reputation": 950, "link": "http://stackoverflow.com/users/2587904/georg-heiler"}, "score": 0, "is_answered": false, "creation_date": 1477758735, "answer_count": 0, "last_activity_date": 1477758735}, "40174033": {"tags": ["python", "file", "pandas", "data-manipulation"], "question_id": 40174033, "title": "Looking for a module to read and manipulate .fcs files in python", "view_count": 13, "link": "http://stackoverflow.com/questions/40174033/looking-for-a-module-to-read-and-manipulate-fcs-files-in-python", "owner": {"profile_image": "https://www.gravatar.com/avatar/aafcc156cd144eefed9b3097453188e5?s=128&d=identicon&r=PG&f=1", "display_name": "Archie", "user_type": "registered", "user_id": 5609221, "reputation": 71, "link": "http://stackoverflow.com/users/5609221/archie"}, "score": 0, "is_answered": false, "creation_date": 1477045055, "answer_count": 0, "last_activity_date": 1477045055}, "40345556": {"tags": ["python", "linux", "python-2.7", "pandas", "jenkins"], "title": "Pandas performance varies between mac and linux", "owner": {"profile_image": "https://www.gravatar.com/avatar/70f98fb23b16862298ea208aedfd18ae?s=128&d=identicon&r=PG&f=1", "display_name": "vks", "user_type": "registered", "accept_rate": 92, "user_id": 3679490, "reputation": 49588, "link": "http://stackoverflow.com/users/3679490/vks"}, "score": 1, "creation_date": 1477928376, "last_edit_date": 1477929820, "last_activity_date": 1477929820, "question_id": 40345556, "view_count": 33, "is_answered": false, "answer_count": 0, "link": "http://stackoverflow.com/questions/40345556/pandas-performance-varies-between-mac-and-linux"}, "40125654": {"tags": ["python", "pandas", "dataframe"], "title": "cant groupby on certain column after merging 2 dataframes in python", "owner": {"profile_image": "https://lh6.googleusercontent.com/-dI2lYFYnXAk/AAAAAAAAAAI/AAAAAAAAARE/QWLhOH_qH4I/photo.jpg?sz=128", "display_name": "Khrystyna Kosenko", "user_type": "registered", "user_id": 6445733, "reputation": 24, "link": "http://stackoverflow.com/users/6445733/khrystyna-kosenko"}, "score": 1, "creation_date": 1476864633, "last_edit_date": 1476867813, "last_activity_date": 1476867813, "question_id": 40125654, "view_count": 31, "is_answered": false, "answer_count": 0, "link": "http://stackoverflow.com/questions/40125654/cant-groupby-on-certain-column-after-merging-2-dataframes-in-python"}, "40195803": {"tags": ["python", "pandas", "dataframe", "module"], "title": "Using functions from modules in pandas dataframe", "owner": {"profile_image": "https://www.gravatar.com/avatar/035c760ea955c2fd227e16351e51cc1a?s=128&d=identicon&r=PG&f=1", "display_name": "Al_Iskander", "user_type": "registered", "accept_rate": 80, "user_id": 6306448, "reputation": 204, "link": "http://stackoverflow.com/users/6306448/al-iskander"}, "score": 0, "creation_date": 1477162196, "last_edit_date": 1477163678, "last_activity_date": 1477163678, "question_id": 40195803, "view_count": 17, "is_answered": false, "answer_count": 0, "link": "http://stackoverflow.com/questions/40195803/using-functions-from-modules-in-pandas-dataframe"}, "40341213": {"tags": ["python", "pandas", "pyspark", "pyspark-sql"], "title": "Aggregating on 5 minute windows in pyspark", "owner": {"profile_image": "https://www.gravatar.com/avatar/b9e39de46b5a7e52e314cbb5008f1fbf?s=128&d=identicon&r=PG&f=1", "display_name": "Menkes", "user_type": "registered", "accept_rate": 56, "user_id": 5563746, "reputation": 109, "link": "http://stackoverflow.com/users/5563746/menkes"}, "score": 0, "creation_date": 1477913059, "last_edit_date": 1477914706, "last_activity_date": 1477914706, "question_id": 40341213, "view_count": 21, "is_answered": false, "answer_count": 0, "link": "http://stackoverflow.com/questions/40341213/aggregating-on-5-minute-windows-in-pyspark"}, "40075230": {"tags": ["python", "python-2.7", "pandas", "numpy", "zipline"], "title": "KeyError: numpy.datetime64 after changing only the month of a datetime (Zipline)", "owner": {"profile_image": "https://www.gravatar.com/avatar/9a7101fe3ba50e621e91ee1edf9d27bb?s=128&d=identicon&r=PG", "display_name": "Nyxynyx", "user_type": "registered", "accept_rate": 72, "user_id": 741099, "reputation": 13529, "link": "http://stackoverflow.com/users/741099/nyxynyx"}, "score": 0, "creation_date": 1476650569, "last_edit_date": 1476652128, "last_activity_date": 1476652128, "question_id": 40075230, "view_count": 20, "is_answered": false, "answer_count": 0, "link": "http://stackoverflow.com/questions/40075230/keyerror-numpy-datetime64-after-changing-only-the-month-of-a-datetime-zipline"}, "40304353": {"tags": ["python", "pandas", "python-ggplot"], "question_id": 40304353, "title": "python ggplot cutting off microseconds", "view_count": 31, "link": "http://stackoverflow.com/questions/40304353/python-ggplot-cutting-off-microseconds", "owner": {"profile_image": "https://www.gravatar.com/avatar/0eed137c407701b13bcba243d691f816?s=128&d=identicon&r=PG&f=1", "display_name": "Frash", "user_type": "registered", "accept_rate": 77, "user_id": 2724299, "reputation": 473, "link": "http://stackoverflow.com/users/2724299/frash"}, "score": 1, "is_answered": false, "creation_date": 1477655002, "answer_count": 0, "last_activity_date": 1477662299}, "40294115": {"tags": ["python", "pandas"], "question_id": 40294115, "title": "Changes in data frame not reflected in csv output", "view_count": 35, "link": "http://stackoverflow.com/questions/40294115/changes-in-data-frame-not-reflected-in-csv-output", "owner": {"profile_image": "https://www.gravatar.com/avatar/9591f4de71c76a92ca769e20bc9282b5?s=128&d=identicon&r=PG&f=1", "display_name": "Dreamer", "user_type": "registered", "accept_rate": 100, "user_id": 6461192, "reputation": 167, "link": "http://stackoverflow.com/users/6461192/dreamer"}, "score": -1, "is_answered": false, "creation_date": 1477602042, "answer_count": 0, "last_activity_date": 1477602042}, "40162277": {"tags": ["python", "pandas", "scikit-learn", "nlp"], "title": "Merge CountVectorizer output from 4 text columns back into one dataset", "owner": {"profile_image": "https://i.stack.imgur.com/LHUAW.jpg?s=128&g=1", "display_name": "Derek Jedamski", "user_type": "registered", "user_id": 4020395, "reputation": 20, "link": "http://stackoverflow.com/users/4020395/derek-jedamski"}, "score": 1, "creation_date": 1476989362, "last_edit_date": 1476996549, "last_activity_date": 1476996549, "question_id": 40162277, "view_count": 43, "is_answered": false, "answer_count": 0, "link": "http://stackoverflow.com/questions/40162277/merge-countvectorizer-output-from-4-text-columns-back-into-one-dataset"}, "40093352": {"tags": ["python", "excel", "bash", "pandas"], "question_id": 40093352, "title": "OpenPyxl Module Needed For DataFrames?", "view_count": 16, "link": "http://stackoverflow.com/questions/40093352/openpyxl-module-needed-for-dataframes", "owner": {"profile_image": "https://www.gravatar.com/avatar/5950ad4c32fd99bec4865d7b8dde2d63?s=128&d=identicon&r=PG&f=1", "display_name": "jerbear", "user_type": "registered", "accept_rate": 88, "user_id": 6876542, "reputation": 15, "link": "http://stackoverflow.com/users/6876542/jerbear"}, "score": 0, "is_answered": false, "creation_date": 1476729297, "answer_count": 0, "last_activity_date": 1476729297}, "40302071": {"tags": ["python", "datetime", "pandas"], "title": "How to add a bolean series to a new column in df2 IF multiple conditions in df1 are met (incl. DATETIME)?", "owner": {"profile_image": "https://graph.facebook.com/10153430563728202/picture?type=large", "display_name": "sudonym", "user_type": "registered", "user_id": 6060083, "reputation": 4, "link": "http://stackoverflow.com/users/6060083/sudonym"}, "score": 0, "creation_date": 1477646836, "last_edit_date": 1477896556, "last_activity_date": 1477896556, "question_id": 40302071, "view_count": 48, "is_answered": false, "answer_count": 0, "link": "http://stackoverflow.com/questions/40302071/how-to-add-a-bolean-series-to-a-new-column-in-df2-if-multiple-conditions-in-df1"}}